task_5_syrkin/__init__.py
task_5_syrkin/collection_app.py
task_5_syrkin-0.0.7.dist-info/entry_points.txt
task_5_syrkin-0.0.7.dist-info/LICENSE
task_5_syrkin-0.0.7.dist-info/WHEEL
task_5_syrkin-0.0.7.dist-info/METADATA
task_5_syrkin-0.0.7.dist-info/RECORD
