Metadata-Version: 2.1
Name: task_5_syrkin
Version: 0.0.6
Summary: Application counts the unique symbols in a string or file.
Author-email: Andrii Syrkin <avvaan1981@gmail.com>
License: The MIT License (MIT)
Project-URL: Home, https://git.foxminded.ua/andrii-syrkin-py_ment/task_5.git
Classifier: License :: OSI Approved :: MIT License
Requires-Python: >=3.12
License-File: LICENSE
Requires-Dist: pytest>=8.3.2
Requires-Dist: coverage>=7.6.1
Requires-Dist: parameterized>=0.9.0
Requires-Dist: argparse>=1.4.0
Requires-Dist: setuptools>=75.1.0
